diode/__init__.py
diode/core.py
diode/main.py
diode/py.typed
diode/test.py
data_diode-0.0.4.dist-info/METADATA
data_diode-0.0.4.dist-info/WHEEL
data_diode-0.0.4.dist-info/entry_points.txt
data_diode-0.0.4.dist-info/top_level.txt
data_diode-0.0.4.dist-info/RECORD
