Metadata-Version: 2.1
Name: data-diode
Version: 0.0.4
Summary: Send and receive data over serial diode
Home-page: https://github.com/fionn/diode
Author: Fionn Fitzmaurice
Project-URL: Source Code, https://github.com/fionn/diode
Project-URL: Changelog, https://github.com/fionn/diode/tags
Project-URL: Documentation, https://github.com/fionn/diode/blob/master/README.md
Project-URL: Bug Tracker, https://github.com/fionn/diode/issues
Project-URL: PyPI, https://pypi.org/project/data-diode/
Project-URL: Download, https://github.com/fionn/diode/archive/refs/heads/master.zip
Keywords: diode,data diode
Classifier: Programming Language :: Python :: 3
Classifier: Development Status :: 4 - Beta
Classifier: Intended Audience :: Developers
Classifier: Topic :: Security
Classifier: Typing :: Typed
Requires-Python: >=3.9
Requires-Dist: pyserial
Provides-Extra: dev
Requires-Dist: pylint ; extra == 'dev'
Requires-Dist: mypy ; extra == 'dev'
Requires-Dist: coverage ; extra == 'dev'
